{
	"name": "Green Fish",
	"icon": "chaosawakens:green_fish",
	"category": "creatures",
	"advancement": "chaosawakens:slay/green_fish",
	"pages": [
		{
			"type": "entity",
			"name": "Green Fish",
			"entity": "chaosawakens:green_fish",
			"scale": 0.5,
			"text": "> $(n)Health:$() 8$(br)> $(n)Attack Damage:$() 0"
		},
		{
			"type": "text",
			"text": "> $(n)Behavior:$() Passive$(br)> $(n)Spawn:$() $(9)Oceans$() in the $(6)Overworld().$(br)> $(n)Drops:$() 1 $(item)Green Fish$()"
		},
		{
			"type": "text",
			"title": "Description",
			"text": "Green Fish are a special kind of fish that you can find in oceans. They don’t really do much apart from swim, give you a new food to eat, and you can put them in buckets for your own uses. Perhaps an aquarium?"
		}
	]
}