{
	"name": "Stink Bug",
	"icon": "chaosawakens:dead_stink_bug",
	"category": "creatures",
	"advancement": "chaosawakens:slay/stink_bug",
	"pages": [
		{
			"type": "entity",
			"name": "Stink Bug",
			"entity": "chaosawakens:stink_bug",
			"scale": 0.75,
			"text": "> $(n)Health:$() 8$(br)> $(n)Attack Damage:$() 0"
		},
		{
			"type": "text",
			"text": "> $(n)Behavior:$() Passive$(br)> $(n)Spawn:$() Forests amd Swamps.$(br)> $(n)Properties:$() $(br)Gives nausea to attackers.$(br)> $(n)Drops:$() 1 $(item)Dead Stink Bug$()"
		},
		{
			"type": "text",
			"title": "Description",
			"text": "Stink Bugs are fascinating creatures that wander swamps and plains. They emit a nauseous stink that causes Nausea when an entity hits them. They’re neat little creatures to watch if you feel like it."
		}
	]
}