{
	"format_version": "1.12.0",
	"minecraft:geometry": [
		{
			"description": {
				"identifier": "geometry.ModelEnt",
				"texture_width": 256,
				"texture_height": 256,
				"visible_bounds_width": 9,
				"visible_bounds_height": 7.5,
				"visible_bounds_offset": [0, 3.25, 0]
			},
			"bones": [
				{
					"name": "Head",
					"pivot": [0, 39, -19],
					"mirror": true,
					"cubes": [
						{"origin": [0, 57.60556, -20.30136], "size": [3, 5, 3], "pivot": [-7, 11, 34], "rotation": [10, 0, 0], "uv": [36, 128], "mirror": false},
						{"origin": [-8, 32, -34], "size": [16, 16, 16], "uv": [0, 0], "mirror": false},
						{"origin": [5, 42.28622, -24.60105], "size": [4, 4, 4], "pivot": [-6, -8, -49], "rotation": [7.5, 0, 0], "uv": [0, 8], "mirror": false},
						{"origin": [5, 42.28622, -20.60105], "size": [4, 4, 7], "pivot": [-6, -8, -49], "rotation": [7.5, 0, 0], "uv": [96, 80], "mirror": false},
						{"origin": [6, 40.60556, -27.30136], "size": [3, 5, 3], "uv": [115, 88], "mirror": false},
						{"origin": [2, 71.60556, 44.69864], "size": [3, 5, 3], "pivot": [-13, 19, 27], "rotation": [80, 0, 0], "uv": [64, 112], "mirror": false},
						{"origin": [1, 80.60556, 49.69864], "size": [3, 5, 3], "pivot": [-9, 17, 31], "rotation": [80, 0, 0], "uv": [12, 128], "mirror": false},
						{"origin": [-1, 78.60556, 52.69864], "size": [3, 5, 3], "pivot": [-9, 13, 31], "rotation": [80, 0, 0], "uv": [115, 88], "mirror": false},
						{"origin": [-4, 88.60556, 81.69864], "size": [3, 5, 3], "pivot": [-19, 7, 56], "rotation": [80, 0, 0], "uv": [127, 89], "mirror": false},
						{"origin": [-2, 75.83031, 49.40575], "size": [3, 3, 3], "pivot": [-9, 20, 31], "rotation": [80, 0, 0], "uv": [12, 136], "mirror": false},
						{"origin": [-5, 72.28622, 51.39895], "size": [4, 4, 4], "pivot": [-20, 19, 27], "rotation": [87.5, 0, 0], "uv": [0, 32], "mirror": false},
						{"origin": [-6, 76.28622, 51.39895], "size": [4, 4, 4], "pivot": [-13, 19, 27], "rotation": [87.5, 0, 0], "uv": [0, 8], "mirror": false},
						{"origin": [-7, 86.60556, 73.69864], "size": [3, 5, 3], "pivot": [-22, 10, 51], "rotation": [80, 0, 0], "uv": [0, 128], "mirror": false},
						{"origin": [-9, 83.60556, 31.69864], "size": [3, 5, 3], "pivot": [-8, 28, 25], "rotation": [80, 0, 0], "uv": [112, 64], "mirror": false},
						{"origin": [-10, 67.28622, 47.39895], "size": [4, 4, 4], "pivot": [-25, 14, 23], "rotation": [87.5, 0, 0], "uv": [0, 0], "mirror": false},
						{"origin": [-11, 94.60556, 69.69864], "size": [3, 5, 3], "pivot": [-12, 17, 53], "rotation": [80, 0, 0], "uv": [115, 88], "mirror": false},
						{"origin": [-9, 34.28622, -18.60105], "size": [4, 4, 4], "pivot": [0, -43, -111], "rotation": [7.5, 0, 0], "uv": [0, 8], "mirror": false},
						{"origin": [-9, 33.28622, -23.60105], "size": [4, 4, 4], "pivot": [-11, -33, -111], "rotation": [7.5, 0, 0], "uv": [0, 8], "mirror": false}
					]
				},
				{
					"name": "MushroomGroupHead1",
					"parent": "Head",
					"pivot": [-8, 73, -10],
					"rotation": [65, 0, 0]
				},
				{
					"name": "MushroomHead1Front",
					"parent": "MushroomGroupHead1",
					"pivot": [-8, 81.45725, -8.42679],
					"rotation": [15, 0, 0]
				},
				{
					"name": "MushroomHead1Back",
					"parent": "MushroomGroupHead1",
					"pivot": [-8, 73, -10]
				},
				{
					"name": "Right_Leg",
					"pivot": [13, 28, 2],
					"mirror": true,
					"cubes": [
						{"origin": [6, 13.46666, -6.13011], "size": [14, 15, 14], "pivot": [13, 20.96666, 0.86989], "rotation": [-12.5, 0, 0], "uv": [146, 18], "mirror": false}
					]
				},
				{
					"name": "right_leg2",
					"parent": "Right_Leg",
					"pivot": [13, 7.5, 0],
					"cubes": [
						{"origin": [6, 0, -7], "size": [14, 15, 14], "inflate": -0.01, "uv": [56, 156]},
						{"origin": [7, 4.60556, 12.69864], "size": [3, 5, 3], "pivot": [-1, -34, -1], "rotation": [10, 0, 0], "uv": [115, 88]},
						{"origin": [11, 5.83031, 13.40575], "size": [3, 3, 3], "pivot": [-1, -34, -1], "rotation": [10, 0, 0], "uv": [24, 136]},
						{"origin": [14, 5.28622, 17.39895], "size": [4, 4, 4], "pivot": [-1, -34, -1], "rotation": [17.5, 0, 0], "uv": [0, 40]},
						{"origin": [18, 5.83031, 11.40575], "size": [3, 3, 3], "pivot": [6, -27, -1], "rotation": [10, 0, 0], "uv": [36, 136]}
					]
				},
				{
					"name": "Left_Leg",
					"pivot": [-14, 27, 2],
					"mirror": true,
					"cubes": [
						{"origin": [-20, 12.46666, -6.13011], "size": [14, 15, 14], "pivot": [-13, 19.96666, 0.86989], "rotation": [-12.5, 0, 0], "uv": [154, 100], "mirror": false},
						{"origin": [-21.75, 11.05725, -15.3002], "size": [5, 2, 5], "pivot": [4, -73.54275, 28.57321], "rotation": [-12.5, 0, 0], "uv": [90, 0], "mirror": false},
						{"origin": [-8, 11.60556, 4.69864], "size": [3, 5, 3], "pivot": [-7, 4, 34], "rotation": [-7.5, 0, 0], "uv": [115, 88], "mirror": false},
						{"origin": [-11, 15.60556, 2.69864], "size": [3, 5, 3], "pivot": [-17, -10, 32], "rotation": [-7.5, 0, 0], "uv": [127, 89], "mirror": false},
						{"origin": [-20, 12.60556, 4.69864], "size": [3, 5, 3], "pivot": [-7, 4, 34], "rotation": [-7.5, 0, 0], "uv": [112, 64], "mirror": false},
						{"origin": [-14, 21.60556, -4.30136], "size": [3, 5, 3], "pivot": [-24, -3, 32], "rotation": [10, 0, 0], "uv": [125, 72], "mirror": false},
						{"origin": [-20, 35.60556, 51.69864], "size": [3, 5, 3], "pivot": [-26, 4, 34], "rotation": [82.5, 0, 0], "uv": [126, 81], "mirror": false}
					]
				},
				{
					"name": "left_leg2",
					"parent": "Left_Leg",
					"pivot": [-13, 7.5, 0],
					"cubes": [
						{"origin": [-20, 0, -7], "size": [14, 15, 14], "inflate": -0.01, "uv": [0, 142]}
					]
				},
				{
					"name": "RightArm",
					"pivot": [18, 40, -18],
					"mirror": true,
					"cubes": [
						{"origin": [18, 20.59836, -23.79828], "size": [14, 22, 14], "pivot": [25, 31.59836, -16.79828], "rotation": [12.5, 0, 0], "uv": [140, 64], "mirror": false},
						{"origin": [18, 32.60556, -10.30136], "size": [3, 5, 3], "pivot": [-7, -25, -9], "rotation": [15, 0, 0], "uv": [124, 64], "mirror": false},
						{"origin": [30, 16.83031, 22.40575], "size": [3, 3, 3], "pivot": [-7, -32, -9], "rotation": [40, 0, 0], "uv": [106, 134], "mirror": false},
						{"origin": [26, 19.83031, 2.40575], "size": [3, 3, 3], "pivot": [-17, -46, -11], "rotation": [10, 0, 0], "uv": [48, 128], "mirror": false},
						{"origin": [24, 89.83031, 58.40575], "size": [3, 3, 3], "pivot": [12, 28, 45], "rotation": [97.5, 0, 0], "uv": [0, 136], "mirror": false},
						{"origin": [28, 78.83031, 52.40575], "size": [3, 3, 3], "pivot": [-9, 20, 36], "rotation": [87.5, 0, 0], "uv": [106, 134], "mirror": false},
						{"origin": [18, 84.60556, 60.69864], "size": [3, 5, 3], "pivot": [8, 32, 43], "rotation": [97.5, 0, 0], "uv": [124, 64], "mirror": false},
						{"origin": [27, 86.28622, 67.39895], "size": [4, 4, 4], "pivot": [12, 33, 43], "rotation": [105, 0, 0], "uv": [0, 8], "mirror": false},
						{"origin": [25, 78.60556, 53.69864], "size": [3, 5, 3], "pivot": [-9, 20, 36], "rotation": [87.5, 0, 0], "uv": [76, 112], "mirror": false},
						{"origin": [-18, 28, -42], "size": [6, 7, 6], "pivot": [0, 0, 0], "rotation": [0, -80, 0], "uv": [72, 2], "mirror": false},
						{"origin": [-15, 35, -39], "size": [0, 5, 6], "pivot": [0, 0, 0], "rotation": [0, -80, 0], "uv": [98, 1], "mirror": false}
					]
				},
				{
					"name": "right_arm_segment",
					"parent": "RightArm",
					"pivot": [28.625, 10.97707, -22.9693],
					"cubes": [
						{"origin": [18, 0.89689, -22.63841], "size": [14, 22, 14], "inflate": -0.01, "pivot": [25, 11.89689, -15.63841], "rotation": [-5, 0, 0], "uv": [106, 134]},
						{"origin": [24, 5.60556, -12.30136], "size": [3, 5, 3], "pivot": [-6, -42, -15], "rotation": [-2.5, 0, 0], "uv": [76, 112]},
						{"origin": [31, 7.83031, 13.40575], "size": [3, 3, 3], "pivot": [-6, -35, -15], "rotation": [27.5, 0, 0], "uv": [12, 136]},
						{"origin": [24, 11.28622, -18.60105], "size": [4, 4, 4], "pivot": [9, -42, -43], "rotation": [5, 0, 0], "uv": [0, 8]},
						{"origin": [30.25, 9.05725, -32.3002], "size": [4, 2, 4], "pivot": [55, -75.54275, 11.57321], "rotation": [-5, 0, 0], "uv": [0, 104]},
						{"origin": [17, 11.28622, -18.60105], "size": [4, 4, 4], "pivot": [2, -42, -43], "rotation": [5, 0, 0], "uv": [0, 32]},
						{"origin": [22, 3.60556, -14.30136], "size": [3, 5, 3], "pivot": [-23, -49, -9], "rotation": [10, 0, 0], "uv": [125, 72]},
						{"origin": [29, 20.60556, -20.30136], "size": [3, 5, 3], "pivot": [8, 4, 6], "rotation": [10, 0, 0], "uv": [64, 112]}
					]
				},
				{
					"name": "LeftArm",
					"pivot": [-18, 41, -18],
					"mirror": true,
					"cubes": [
						{"origin": [-32, 20.59836, -23.79828], "size": [14, 22, 14], "pivot": [-25, 31.59836, -16.79828], "rotation": [12.5, 0, 0], "uv": [50, 120], "mirror": false},
						{"origin": [-34.75, 46.05725, -10.3002], "size": [5, 2, 5], "pivot": [-9, -38.54275, 33.57321], "rotation": [12.5, 0, 0], "uv": [48, 8], "mirror": false},
						{"origin": [23, 26, -28], "size": [6, 7, 6], "pivot": [0, 0, 0], "rotation": [-180, 60, 180], "uv": [72, 2], "mirror": false},
						{"origin": [26, 33, -25], "size": [0, 5, 6], "pivot": [0, 0, 0], "rotation": [-180, 60, 180], "uv": [98, 1], "mirror": false},
						{"origin": [-32, 18, -30], "size": [6, 7, 6], "uv": [72, 2], "mirror": false},
						{"origin": [-29, 25, -27], "size": [0, 5, 6], "uv": [98, 1], "mirror": false},
						{"origin": [-29, 38.83031, -13.59425], "size": [3, 3, 3], "pivot": [-40, -8, -28], "rotation": [10, 0, 0], "uv": [106, 134], "mirror": false},
						{"origin": [-32, -33.39444, 16.69864], "size": [3, 5, 3], "pivot": [-40, -8, -28], "rotation": [105, 0, 0], "uv": [76, 112], "mirror": false},
						{"origin": [-30, 35.28622, -3.60105], "size": [4, 4, 4], "pivot": [-33, -1, -28], "rotation": [17.5, 0, 0], "uv": [0, 8], "mirror": false},
						{"origin": [-33, 27.28622, 2.39895], "size": [5, 4, 4], "pivot": [-47, -26, -22], "rotation": [17.5, 0, 0], "uv": [111, 76], "mirror": false},
						{"origin": [-34, 24.60556, -4.30136], "size": [3, 5, 3], "pivot": [-42, -28, -22], "rotation": [10, 0, 0], "uv": [126, 81], "mirror": false}
					]
				},
				{
					"name": "left_arm_segment",
					"parent": "LeftArm",
					"pivot": [-25, 11.88928, -15.4641],
					"cubes": [
						{"origin": [-32, 0.88928, -22.4641], "size": [14, 22, 14], "inflate": -0.01, "pivot": [-25, 11.88928, -15.4641], "rotation": [-5, 0, 0], "uv": [98, 98]},
						{"origin": [-34, -3.71378, -4.60105], "size": [4, 4, 4], "pivot": [-49, -57, -29], "rotation": [17.5, 0, 0], "uv": [0, 32]},
						{"origin": [-30, -1.16969, -10.59425], "size": [3, 3, 3], "pivot": [-42, -57, -29], "rotation": [10, 0, 0], "uv": [0, 136]},
						{"origin": [-34, 11.28622, -11.60105], "size": [4, 4, 4], "uv": [0, 72]},
						{"origin": [-35, 19.28622, -4.60105], "size": [4, 4, 4], "pivot": [-32, -35, -2], "rotation": [17.5, 0, 0], "uv": [0, 64]}
					]
				},
				{
					"name": "Body",
					"pivot": [0, 11, 34],
					"rotation": [65, 0, 0]
				},
				{
					"name": "Chest",
					"parent": "Body",
					"pivot": [-8, 73, 26],
					"mirror": true,
					"cubes": [
						{"origin": [-8, 57, 26], "size": [16, 16, 16], "uv": [96, 32], "mirror": false}
					]
				},
				{
					"name": "LeftPelvis",
					"parent": "Chest",
					"pivot": [-16, 57, 26],
					"mirror": true,
					"cubes": [
						{"origin": [-16, 41, 26], "size": [16, 16, 16], "uv": [96, 0], "mirror": false}
					]
				},
				{
					"name": "RightPelvis",
					"parent": "Chest",
					"pivot": [0, 57, 26],
					"mirror": true,
					"cubes": [
						{"origin": [0, 41, 26], "size": [16, 16, 16], "uv": [0, 96], "mirror": false}
					]
				},
				{
					"name": "MushroomGroupBody1",
					"parent": "RightPelvis",
					"pivot": [13, 28.75461, 70.21437],
					"rotation": [-17.5, 0, 0]
				},
				{
					"name": "MushroomBody1Middle2",
					"parent": "MushroomGroupBody1",
					"pivot": [13, 37.21186, 71.78758],
					"rotation": [15, 0, 0]
				},
				{
					"name": "MushroomBody1Font3",
					"parent": "MushroomGroupBody1",
					"pivot": [32, 38.07251, 68.28626],
					"rotation": [15, 27.5, 0]
				},
				{
					"name": "MushroomBody1Back2",
					"parent": "MushroomGroupBody1",
					"pivot": [13, 28.75461, 70.21437]
				},
				{
					"name": "RightAb",
					"parent": "Chest",
					"pivot": [2, 73, 24],
					"mirror": true,
					"cubes": [
						{"origin": [2, 57, 24], "size": [16, 16, 16], "inflate": -0.01, "uv": [48, 80], "mirror": false}
					]
				},
				{
					"name": "Left_Ab",
					"parent": "Chest",
					"pivot": [-18, 73, 24],
					"mirror": true,
					"cubes": [
						{"origin": [-18, 57, 24], "size": [16, 16, 16], "inflate": -0.01, "uv": [0, 64], "mirror": false}
					]
				},
				{
					"name": "StomachAbs",
					"parent": "Chest",
					"pivot": [-8, 57, 24],
					"mirror": true,
					"cubes": [
						{"origin": [-8, 41, 24], "size": [16, 16, 16], "inflate": -0.01, "uv": [48, 48], "mirror": false}
					]
				},
				{
					"name": "Right_Shoulderblade",
					"parent": "Chest",
					"pivot": [2, 73, 27],
					"mirror": true,
					"cubes": [
						{"origin": [2, 57, 27], "size": [16, 16, 16], "uv": [48, 16], "mirror": false}
					]
				},
				{
					"name": "leaf",
					"parent": "Right_Shoulderblade",
					"pivot": [0, 11, 34],
					"cubes": [
						{"origin": [12, 56.83031, 50.40575], "size": [3, 3, 3], "pivot": [0, 11, 34], "rotation": [10, 0, 0], "uv": [134, 69]},
						{"origin": [12, 64.60556, 51.69864], "size": [3, 5, 3], "pivot": [-3, 12, 34], "rotation": [10, 0, 0], "uv": [64, 112]},
						{"origin": [3, 50.60556, 47.69864], "size": [3, 5, 3], "pivot": [-7, 11, 34], "rotation": [10, 0, 0], "uv": [12, 128]},
						{"origin": [12, 43.83031, 46.40575], "size": [3, 3, 3], "pivot": [0, 11, 34], "rotation": [10, 0, 0], "uv": [36, 136]},
						{"origin": [-14, 49.60556, 49.69864], "size": [3, 5, 3], "pivot": [-24, -3, 32], "rotation": [10, 0, 0], "uv": [125, 72]},
						{"origin": [-9, 50.28622, 56.39895], "size": [4, 4, 4], "pivot": [-24, -3, 32], "rotation": [17.5, 0, 0], "uv": [0, 96]},
						{"origin": [-2, 49.60556, 49.69864], "size": [3, 5, 3], "pivot": [-17, -3, 32], "rotation": [10, 0, 0], "uv": [0, 128]},
						{"origin": [-9, 43.28622, 56.39895], "size": [4, 4, 4], "pivot": [-24, -10, 32], "rotation": [17.5, 0, 0], "uv": [0, 0]},
						{"origin": [-5, 45.83031, 50.40575], "size": [3, 3, 3], "pivot": [-17, -10, 32], "rotation": [10, 0, 0], "uv": [48, 128]},
						{"origin": [-16, 59.28622, 58.39895], "size": [4, 4, 4], "pivot": [-31, 6, 34], "rotation": [17.5, 0, 0], "uv": [0, 72]},
						{"origin": [-9, 58.60556, 51.69864], "size": [3, 5, 3], "pivot": [-24, 6, 34], "rotation": [10, 0, 0], "uv": [24, 128]},
						{"origin": [1, 56.60556, 51.69864], "size": [3, 5, 3], "pivot": [-7, 4, 34], "rotation": [10, 0, 0], "uv": [76, 112]},
						{"origin": [-11, 64.28622, 58.39895], "size": [4, 4, 4], "pivot": [-26, 11, 34], "rotation": [17.5, 0, 0], "uv": [0, 64]},
						{"origin": [-7, 56.83031, 50.40575], "size": [3, 3, 3], "pivot": [-19, 11, 34], "rotation": [10, 0, 0], "uv": [106, 140]},
						{"origin": [-18, 56.60556, 51.69864], "size": [3, 5, 3], "pivot": [-26, 4, 34], "rotation": [10, 0, 0], "uv": [126, 81]},
						{"origin": [-11, 41.60556, 47.69864], "size": [3, 5, 3], "pivot": [-7, 4, 34], "rotation": [10, 0, 0], "uv": [112, 64]},
						{"origin": [14, 60.83031, 52.40575], "size": [3, 3, 3], "pivot": [2, 5, 34], "rotation": [10, 0, 0], "uv": [48, 128]},
						{"origin": [10, 58.28622, 58.39895], "size": [4, 4, 4], "pivot": [-5, 5, 34], "rotation": [17.5, 0, 0], "uv": [0, 0]},
						{"origin": [8, 56.60556, 49.69864], "size": [3, 5, 3], "pivot": [12, 19, 36], "rotation": [10, 0, 0], "uv": [112, 64]},
						{"origin": [0, 45.60556, 45.69864], "size": [3, 5, 3], "pivot": [-3, 12, 34], "rotation": [10, 0, 0], "uv": [64, 112]},
						{"origin": [2, 41.83031, 46.40575], "size": [3, 3, 3], "pivot": [2, 5, 34], "rotation": [10, 0, 0], "uv": [48, 128]},
						{"origin": [-4, 37.60556, 43.69864], "size": [3, 5, 3], "pivot": [12, 19, 36], "rotation": [10, 0, 0], "uv": [112, 64]},
						{"origin": [0, 37.83031, 44.40575], "size": [3, 3, 3], "pivot": [0, 11, 34], "rotation": [10, 0, 0], "uv": [134, 69]},
						{"origin": [-17, 60.60556, 52.69864], "size": [12, 5, 3], "pivot": [-7, 4, 34], "rotation": [27.5, 0, 0], "uv": [48, 0]},
						{"origin": [-11, 65.60556, 52.69864], "size": [3, 5, 3], "pivot": [-7, 4, 34], "rotation": [10, 0, 0], "uv": [112, 64]},
						{"origin": [5, 59.83031, 52.40575], "size": [3, 3, 3], "pivot": [-7, 4, 34], "rotation": [10, 0, 0], "uv": [106, 134]},
						{"origin": [13, 69.83031, 51.40575], "size": [3, 3, 3], "pivot": [-7, 4, 34], "rotation": [10, 0, 0], "uv": [106, 134]},
						{"origin": [10, 69.83031, 46.40575], "size": [3, 3, 3], "pivot": [-7, 4, 34], "rotation": [10, 0, 0], "uv": [106, 134]},
						{"origin": [0, 50.83031, 48.40575], "size": [3, 3, 3], "pivot": [-7, 11, 34], "rotation": [10, 0, 0], "uv": [140, 100]},
						{"origin": [0, 50.83031, 30.40575], "size": [3, 3, 3], "pivot": [-7, 11, 34], "rotation": [10, 0, 0], "uv": [140, 100]},
						{"origin": [-5, 45.83031, 32.40575], "size": [3, 3, 3], "pivot": [-17, -10, 32], "rotation": [10, 0, 0], "uv": [48, 128]},
						{"origin": [-2, 42.60556, 31.69864], "size": [3, 5, 3], "pivot": [-17, -10, 32], "rotation": [10, 0, 0], "uv": [127, 89]},
						{"origin": [5, 43.83031, 48.40575], "size": [3, 3, 3], "pivot": [-7, 4, 34], "rotation": [10, 0, 0], "uv": [24, 136]},
						{"origin": [8, 43.28622, 52.39895], "size": [4, 4, 4], "pivot": [-7, 4, 34], "rotation": [17.5, 0, 0], "uv": [0, 40]},
						{"origin": [-4, 34, -58], "size": [19, 17, 0], "pivot": [0, 0, 0], "rotation": [-67.5, 0, 0], "uv": [154, 129]}
					]
				},
				{
					"name": "Left_Shoulderblade",
					"parent": "Chest",
					"pivot": [-18, 73, 27],
					"mirror": true,
					"cubes": [
						{"origin": [-18, 57, 27], "size": [16, 16, 16], "uv": [0, 32], "mirror": false}
					]
				},
				{
					"name": "CocoaBeans",
					"pivot": [0, 0, 0]
				}
			]
		}
	]
}