{
  "type": "minecraft:block",
  "pools": [
    {
      "bonus_rolls": 0.0,
      "entries": [
        {
          "type": "minecraft:item",
          "functions": [
            {
              "add": false,
              "conditions": [
                {
                  "block": "chaosawakens:apple_slab",
                  "condition": "minecraft:block_state_property",
                  "properties": {
                    "type": "double"
                  }
                }
              ],
              "count": 2.0,
              "function": "minecraft:set_count"
            }
          ],
          "name": "chaosawakens:apple_slab"
        }
      ],
      "functions": [
        {
          "function": "minecraft:explosion_decay"
        }
      ],
      "rolls": 1.0
    }
  ],
  "random_sequence": "chaosawakens:blocks/apple_slab"
}